{
    "_id": "ETH-1-0x8b9c35c79af5319c70dd9a3e3850f368822ed64e",
    "address": "0x8b9c35c79af5319c70dd9a3e3850f368822ed64e",
    "type": "token",
    "format": "ERC20",
    "explorer": [
        "https:\/\/etherscan.io\/token\/0x8b9c35c79af5319c70dd9a3e3850f368822ed64e"
    ],
    "links": [],
    "tags": [],
    "description": "",
    "date": "2018-01-02T13:28:57+00:00",
    "icon": "icons\/dogetoken_28.png",
    "name": "DogeToken",
    "totalSupply": "93055",
    "symbol": "DGT",
    "reputation": "UNKNOWN"
}