{
    "_id": "ETH-1-0xce59d29b09aae565feeef8e52f47c3cd5368c663",
    "address": "0xce59d29b09aae565feeef8e52f47c3cd5368c663",
    "type": "token",
    "format": "ERC20",
    "explorer": [
        "https:\/\/etherscan.io\/token\/0xce59d29b09aae565feeef8e52f47c3cd5368c663"
    ],
    "links": [],
    "tags": [],
    "description": "",
    "date": "2018-01-02T13:29:26+00:00",
    "icon": "icons\/bullioncoin_28.png",
    "name": "BullionCoin",
    "totalSupply": "100000000",
    "symbol": "BLX",
    "reputation": "NEUTRAL"
}